tags2sdists/__init__.py
tags2sdists/checkoutdir.py
tags2sdists/packagedir.py
tags2sdists/script.py
tags2sdists/utils.py
tags2sdists-2.6.0.dist-info/LICENSE.rst
tags2sdists-2.6.0.dist-info/METADATA
tags2sdists-2.6.0.dist-info/WHEEL
tags2sdists-2.6.0.dist-info/entry_points.txt
tags2sdists-2.6.0.dist-info/top_level.txt
tags2sdists-2.6.0.dist-info/RECORD
