Metadata-Version: 2.2
Name: tags2sdists
Version: 2.6.0
Summary: Create python sdists from tags
Author-email: Reinout van Rees <reinout@vanrees.org>
License:                     GNU GENERAL PUBLIC LICENSE
Project-URL: Repository, https://github.com/lizardsystem/tags2sdists/
Requires-Python: >=3.12
License-File: LICENSE.rst
Requires-Dist: packaging>=24.2
Requires-Dist: pkginfo
Requires-Dist: setuptools
Requires-Dist: zest.releaser>=9.4.0
